igenerator/__init__.py
igenerator/generate.py
igenerator-0.0.2.dist-info/LICENSE
igenerator-0.0.2.dist-info/METADATA
igenerator-0.0.2.dist-info/WHEEL
igenerator-0.0.2.dist-info/top_level.txt
igenerator-0.0.2.dist-info/RECORD
