Metadata-Version: 2.1
Name: igenerator
Version: 0.0.2
Summary: Generating random numbers faster than numpy
Author: Mahimai Raja J ( iKurious )
Author-email: <info@mahimairaja.in>
Keywords: python,random generator,numbers,machine learning,database,data generator
Classifier: Development Status :: 1 - Planning
Classifier: Intended Audience :: Developers
Classifier: Programming Language :: Python :: 3
Classifier: Operating System :: Unix
Classifier: Operating System :: MacOS :: MacOS X
Classifier: Operating System :: Microsoft :: Windows
License-File: LICENSE
Requires-Dist: jax
Requires-Dist: jaxlib
Requires-Dist: numpyro
